hydra_plugins/__init__.py
hydra_plugins/hydra_logzio_logger/__init__.py
hydra_plugins/hydra_logzio_logger/logzio_logger_path_plugin.py
hydra_plugins/hydra_logzio_logger/conf/__init__.py
hydra_plugins/hydra_logzio_logger/conf/hydra/__init__.py
hydra_plugins/hydra_logzio_logger/conf/hydra/hydra_logging/__init__.py
hydra_plugins/hydra_logzio_logger/conf/hydra/hydra_logging/logzio_logger.yaml
hydra_plugins/hydra_logzio_logger/conf/hydra/job_logging/__init__.py
hydra_plugins/hydra_logzio_logger/conf/hydra/job_logging/logzio_logger.yaml
hydra_logzio_logger-0.0.2.dist-info/LICENSE
hydra_logzio_logger-0.0.2.dist-info/METADATA
hydra_logzio_logger-0.0.2.dist-info/WHEEL
hydra_logzio_logger-0.0.2.dist-info/top_level.txt
hydra_logzio_logger-0.0.2.dist-info/RECORD
