Metadata-Version: 2.1
Name: hydra-logzio-logger
Version: 0.0.2
Summary: hydra-logzio-logger, hydra plugin to log into logzio server
Home-page: https://github.com/shay-te/hydra-logzio-logger
Author: Shay Tessler
Author-email: shay.te@gmail.com
License: MIT
Platform: UNKNOWN
Classifier: Programming Language :: Python :: 3
Classifier: License :: OSI Approved :: MIT License
Classifier: Operating System :: OS Independent
Requires-Python: >=3.7
Requires-Dist: logzio-python-handler
